palpao_server/__init__.py
palpao_server/__version__.py
palpao_server/calib/modal_basis/diag241.fits
palpao_server/calib/modulator/pi_calibration.py
palpao_server/calib/zonal_command/zero.fits
palpao_server/conf/palpao_server.conf
palpao_server/mirror_controller/__init__.py
palpao_server/mirror_controller/abstract_deformable_mirror.py
palpao_server/mirror_controller/abstract_modulator.py
palpao_server/mirror_controller/alpao_deformable_mirror.py
palpao_server/mirror_controller/bmc_deformable_mirror.py
palpao_server/mirror_controller/deformable_mirror_controller.py
palpao_server/mirror_controller/fake_alpao_dm.py
palpao_server/mirror_controller/fake_bmc_dm.py
palpao_server/mirror_controller/palpao_run_mirror_controller.py
palpao_server/mirror_controller/pi_S334_modulator.py
palpao_server/mirror_controller/pi_tip_tilt_mirror.py
palpao_server/mirror_controller/runner.py
palpao_server/mirror_controller/simulated_deformable_mirror.py
palpao_server/process_monitor/__init__.py
palpao_server/process_monitor/palpao_run_process_monitor.py
palpao_server/process_monitor/runner.py
palpao_server/scripts/__init__.py
palpao_server/scripts/palpao_kill_processes.py
palpao_server/scripts/palpao_mirror_controller_1.py
palpao_server/scripts/palpao_mirror_controller_2.py
palpao_server/scripts/palpao_process_monitor.py
palpao_server/scripts/palpao_stop.py
palpao_server/utils/__init__.py
palpao_server/utils/constants.py
palpao_server/utils/process_startup_helper.py
palpao_server/utils/starter_script_creator.py
palpao_server-0.16.1.dist-info/DESCRIPTION.rst
palpao_server-0.16.1.dist-info/METADATA
palpao_server-0.16.1.dist-info/RECORD
palpao_server-0.16.1.dist-info/WHEEL
palpao_server-0.16.1.dist-info/entry_points.txt
palpao_server-0.16.1.dist-info/metadata.json
palpao_server-0.16.1.dist-info/top_level.txt
