Metadata-Version: 2.0
Name: palpao-server
Version: 0.16.1
Summary: ALPAO, Boston MEMS, Physik Instrument Deformable mirrors interface
Home-page: https://github.com/lbusoni/palpao_server
Author: Lorenzo Busoni
Author-email: lorenzo.busoni@inaf.it
License: MIT
Keywords: plico, deformable mirror, ALPAO, Boston MEMS, Physik Instrument, piezo, laboratory, instrumentation control
Platform: UNKNOWN
Classifier: Development Status :: 4 - Beta
Classifier: Operating System :: POSIX :: Linux
Classifier: Programming Language :: Python :: 2.7
Classifier: Programming Language :: Python :: 3.5
Classifier: Programming Language :: Python :: 3.6
Requires-Dist: plico (>=0.15)
Requires-Dist: palpao (>=0.16)
Requires-Dist: numpy
Requires-Dist: scipy
Requires-Dist: psutil
Requires-Dist: six
Requires-Dist: pyfits
Requires-Dist: pi-gcs
